Workbook

Sheet Company 01-01-21 to 31-12-25
A1: Date | B1: Open Price | C1: High Price | D1: Low Price | E1: Close Price | F1: WAP | G1: No.of Shares | H1: No. of Trades | I1: Total Turnover (Rs.) | J1: Deliverable Quantity | K1: % Deli. Qty to Traded Qty | L1: Spread High-Low | M1: Spread Close-Open
A2: 44197 | B2: 33 | C2: 33.9 | D2: 33 | E2: 33.1 | F2: 33.279063 | G2: 14219 | H2: 72 | I2: 473195 | J2: 9315 | K2: 65.51 | L2: 0.9 | M2: 0.1
A3: 44200 | B3: 33.9 | C3: 34 | D3: 32 | E3: 32.2 | F3: 33.048506 | G3: 26471 | H3: 103 | I3: 874827 | J3: 21948 | K3: 82.91 | L3: 2 | M3: -1.7
A4: 44201 | B4: 32.2 | C4: 32.95 | D4: 31.1 | E4: 31.95 | F4: 32.168497 | G4: 25496 | H4: 69 | I4: 820168 | J4: 23428 | K4: 91.89 | L4: 1.85 | M4: -0.25
A5: 44202 | B5: 31.95 | C5: 32.3 | D5: 30.5 | E5: 30.9 | F5: 31.260404 | G5: 17469 | H5: 75 | I5: 546088 | J5: 15016 | K5: 85.96 | L5: 1.8 | M5: -1.05
A6: 44203 | B6: 32 | C6: 35.9 | D6: 29.15 | E6: 33.9 | F6: 33.26711 | G6: 213878 | H6: 861 | I6: 7115103 | J6: 96814 | K6: 45.27 | L6: 6.75 | M6: 1.9
A7: 44204 | B7: 35.5 | C7: 35.6 | D7: 32.2 | E7: 33.05 | F7: 34.356203 | G7: 29938 | H7: 223 | I7: 1028556 | J7: 22424 | K7: 74.9 | L7: 3.4 | M7: -2.45
A8: 44207 | B8: 34.95 | C8: 35 | D8: 32.5 | E8: 32.85 | F8: 33.556155 | G8: 26525 | H8: 165 | I8: 890077 | J8: 19887 | K8: 74.97 | L8: 2.5 | M8: -2.1
A9: 44208 | B9: 32 | C9: 32.65 | D9: 31.25 | E9: 32.05 | F9: 32.061391 | G9: 13471 | H9: 71 | I9: 431899 | J9: 12322 | K9: 91.47 | L9: 1.4 | M9: 0.05
A10: 44209 | B10: 31.45 | C10: 32.25 | D10: 31 | E10: 31.2 | F10: 31.447238 | G10: 17778 | H10: 87 | I10: 559069 | J10: 16055 | K10: 90.31 | L10: 1.25 | M10: -0.25
A11: 44210 | B11: 32.4 | C11: 32.4 | D11: 28.35 | E11: 29.75 | F11: 30.154581 | G11: 19776 | H11: 134 | I11: 596337 | J11: 18350 | K11: 92.79 | L11: 4.05 | M11: -2.65
A12: 44211 | B12: 27.2 | C12: 29.5 | D12: 27.2 | E12: 29.25 | F12: 28.817923 | G12: 13357 | H12: 56 | I12: 384921 | J12: 12457 | K12: 93.26 | L12: 2.3 | M12: 2.05
A13: 44214 | B13: 29 | C13: 29.9 | D13: 29 | E13: 29.1 | F13: 29.245861 | G13: 9965 | H13: 47 | I13: 291435 | J13: 9265 | K13: 92.98 | L13: 0.9 | M13: 0.1
... A1241: 46022 | B1241: 335 | C1241: 335.95 | D1241: 331.8 | E1241: 334 | F1241: 334.22231 | G1241: 4026 | H1241: 286 | I1241: 1345579 | J1241: 2406 | K1241: 59.76 | L1241: 4.15 | M1241: -1

Sheet Market 01-01-21 to 31-12-25
A1: Date | B1: Open | C1: High | D1: Low | E1: Close | F1: Points Change | G1: Change(%) | H1: Volume(Cr.) | I1: Turnover (Rs.Cr.) | J1: P/E | K1: P/B | L1: Div Yield
A2: 44197 | B2: 47785.28 | C2: 47980.36 | D2: 47771.15 | E2: 47868.98 | F2: 117.65 | G2: 0.25 | H2: 0.83 | I2: 524.96 | J2: 33.5 | K2: 3.27 | L2: 0.83
A3: 44200 | B3: 48109.17 | C3: 48220.47 | D3: 47594.47 | E3: 48176.8 | F3: 307.82 | G3: 0.64 | H3: 1.39 | I3: 809.27 | J3: 33.68 | K3: 3.29 | L3: 0.82
A4: 44201 | B4: 48037.63 | C4: 48486.24 | D4: 47903.38 | E4: 48437.78 | F4: 260.98 | G4: 0.54 | H4: 1.22 | I4: 932.63 | J4: 33.76 | K4: 3.3 | L4: 0.82
A5: 44202 | B5: 48616.66 | C5: 48616.66 | D5: 47864.14 | E5: 48174.06 | F5: -263.72 | G5: -0.54 | H5: - | J5: 33.59 | K5: 3.28 | L5: 0.83
A6: 44203 | B6: 48524.36 | C6: 48558.34 | D6: 48037.87 | E6: 48093.32 | F6: -80.74 | G6: -0.17 | H6: 1.84 | I6: 1417.49 | J6: 33.51 | K6: 3.27 | L6: 0.83
A7: 44204 | B7: 48464.91 | C7: 48854.34 | D7: 48365.58 | E7: 48782.51 | F7: 689.19 | G7: 1.43 | H7: 2.22 | I7: 1716.24 | J7: 33.93 | K7: 3.31 | L7: 0.82
A8: 44207 | B8: 49252.31 | C8: 49303.79 | D8: 48956.38 | E8: 49269.32 | F8: 486.81 | G8: 1 | H8: 2.12 | I8: 1605.22 | J8: 34.32 | K8: 3.37 | L8: 0.81
A9: 44208 | B9: 49228.26 | C9: 49569.14 | D9: 49079.57 | E9: 49517.11 | F9: 247.79 | G9: 0.5 | H9: 1.27 | I9: 940.52 | J9: 34.55 | K9: 3.39 | L9: 0.8
A10: 44209 | B10: 49763.93 | C10: 49795.19 | D10: 49073.85 | E10: 49492.32 | F10: -24.79 | G10: -0.05 | H10: 2.72 | I10: 1611.31 | J10: 34.65 | K10: 3.4 | L10: 0.8
A11: 44210 | B11: 49432.83 | C11: 49663.58 | D11: 49182.37 | E11: 49584.16 | F11: 91.84 | G11: 0.19 | H11: - | J11: 34.63 | K11: 3.4 | L11: 0.8
A12: 44211 | B12: 49656.71 | C12: 49656.71 | D12: 48795.79 | E12: 49034.67 | F12: -549.49 | G12: -1.11 | H12: 1.47 | I12: 1266.97 | J12: 34.12 | K12: 3.35 | L12: 0.81
A13: 44214 | B13: 49061.22 | C13: 49122.23 | D13: 48403.97 | E13: 48564.27 | F13: -470.4 | G13: -0.96 | H13: 1.66 | I13: 1187.8 | J13: 33.47 | K13: 3.3 | L13: 0.82
A14: 44215 | B14: 48900.31 | C14: 49499.86 | D14: 48805.54 | E14: 49398.29 | F14: 834.02 | G14: 1.72 | H14: - | J14: 34.08 | K14: 3.36 | L14: 0.81
A15: 44216 | B15: 49508.79 | C15: 49874.42 | D15: 49373.68 | E15: 49792.12 | F15: 393.83 | G15: 0.8 | H15: 1.22 | I15: 1402.16 | J15: 34.42 | K15: 3.39 | L15: 0.8
A16: 44217 | B16: 50096.57 | C16: 50184.01 | D16: 49398.86 | E16: 49624.76 | F16: -167.36 | G16: -0.34 | H16: 1.93 | I16: 1709.66 | J16: 34.36 | K16: 3.38 | L16: 0.8
A17: 44218 | B17: 49594.95 | C17: 49676.88 | D17: 48832.08 | E17: 48878.54 | F17: -746.22 | G17: -1.5 | H17: 1.84 | I17: 1486.69 | J17: 33.76 | K17: 3.32 | L17: 0.81
A18: 44221 | B18: 49253.68 | C18: 49263.15 | D18: 48274.92 | E18: 48347.59 | F18: -530.95 | G18: -1.09 | H18: 1.55 | I18: 1432.04 | J18: 33.13 | K18: 3.29 | L18: 0.82
A19: 44223 | B19: 48385.28 | C19: 48387.25 | D19: 47269.6 | E19: 47409.93 | F19: -937.66 | G19: -1.94 | H19: 1.96 | I19: 1444.17 | J19: 32.46 | K19: 3.23 | L19: 0.84
A20: 44224 | B20: 46834.57 | C20: 47172.02 | D20: 46518.48 | E20: 46874.36 | F20: -535.57 | G20: -1.13 | H20: 2.5 | I20: 2471.27 | J20: 31.96 | K20: 3.18 | L20: 0.85
A21: 44225 | B21: 47423.47 | C21: 47423.66 | D21: 46160.46 | E21: 46285.77 | F21: -588.59 | G21: -1.26 | H21: 1.45 | I21: 1155.6 | J21: 31.75 | K21: 3.15 | L21: 0.86
A22: 44228 | B22: 46617.95 | C22: 48764.4 | D22: 46433.65 | E22: 48600.61 | F22: 2314.84 | G22: 5 | H22: 2.2 | I22: 1754.31 | J22: 33.08 | K22: 3.3 | L22: 0.82
A23: 44229 | B23: 49193.26 | C23: 50154.48 | D23: 49193.26 | E23: 49797.72 | F23: 1197.11 | G23: 2.46 | H23: 2.84 | I23: 2138.24 | J23: 33.92 | K23: 3.38 | L23: 0.8
A24: 44230 | B24: 50231.06 | C24: 50526.39 | D24: 49515.88 | E24: 50255.75 | F24: 458.03 | G24: 0.92 | H24: 2.24 | I24: 1511.42 | J24: 34.15 | K24: 3.41 | L24: 0.79
A25: 44231 | B25: 50212.25 | C25: 50687.51 | D25: 49926.45 | E25: 50614.29 | F25: 358.54 | G25: 0.71 | H25: 3.36 | I25: 2663.16 | J25: 34.42 | K25: 3.43 | L25: 0.79
A26: 44232 | B26: 51031.39 | C26: 51073.27 | D26: 50565.29 | E26: 50731.63 | F26: 117.34 | G26: 0.23 | H26: 3.22 | I26: 1869.14 | J26: 34.26 | K26: 3.43 | L26: 0.79
... A30: 44238 | B30: 51165.84 | C30: 51592.45 | D30: 51157.31 | E30: 51531.52 | F30: 222.13 | G30: 0.43 | H30: 1.21 | I30: 1131.41 | J30: 35.8 | K30: 3.48 | L30: 0.79
A31: 44239 | B31: 51614.77 | C31: 51804.58 | D31: 51260.62 | E31: 51544.3 | F31: 12.78 | G31: 0.02 | H31: - | J31: 35.79 | K31: 3.48 | L31: 0.79
A32: 44242 | B32: 51907.75 | C32: 52235.97 | D32: 51886.46 | E32: 52154.13 | F32: 609.83 | G32: 1.18 | H32: 1.47 | I32: 1078.13 | J32: 36.21 | K32: 3.52 | L32: 0.71
A33: 44243 | B33: 52400.03 | C33: 52516.76 | D33: 51863.61 | E33: 52104.17 | F33: -49.96 | G33: -0.1 | H33: 2.11 | I33: 1248.34 | J33: 36.13 | K33: 3.51 | L33: 0.71
A34: 44244 | B34: 51996.94 | C34: 52078.15 | D34: 51586.34 | E34: 51703.83 | F34: -400.34 | G34: -0.77 | H34: 1.36 | I34: 1111.59 | J34: 36.01 | K34: 3.49 | L34: 0.69
A35: 44245 | B35: 51903.96 | C35: 51903.96 | D35: 51186.68 | E35: 51324.69 | F35: -379.14 | G35: -0.73 | H35: 1.82 | I35: 1046.63 | J35: 35.9 | K35: 3.48 | L35: 0.7
A36: 44246 | B36: 51238.02 | C36: 51432.99 | D36: 50624.33 | E36: 50889.76 | F36: -434.93 | G36: -0.85 | H36: 1.5 | I36: 961.98 | J36: 35.64 | K36: 3.45 | L36: 0.7
A37: 44249 | B37: 50910.51 | C37: 50986.03 | D37: 49617.37 | E37: 49744.32 | F37: -1145.44 | G37: -2.25 | H37: 1.63 | I37: 1111.76 | J37: 34.76 | K37: 3.37 | L37: 0.72
A38: 44250 | B38: 49994.85 | C38: 50327.31 | D38: 49659.85 | E38: 49751.41 | F38: 7.09 | G38: 0.01 | H38: - | J38: 34.79 | K38: 3.37 | L38: 0.72
A39: 44251 | B39: 49763.94 | C39: 50881.17 | D39: 49648.78 | E39: 50781.69 | F39: 1030.28 | G39: 2.07 | H39: 4.59 | I39: 3805.89 | J39: 35.46 | K39: 3.43 | L39: 0.71
A40: 44252 | B40: 51207.61 | C40: 51386.12 | D40: 50991.76 | E40: 51039.31 | F40: 257.62 | G40: 0.51 | H40: 3.35 | I40: 2624.1 | J40: 35.6 | K40: 3.45 | L40: 0.7
A41: 44253 | B41: 50256.71 | C41: 50400.31 | D41: 48890.48 | E41: 49099.99 | F41: -1939.32 | G41: -3.8 | H41: 2.31 | I41: 1634.09 | J41: 33.86 | K41: 3.28 | L41: 0.74
A42: 44256 | B42: 49747.71 | C42: 50058.42 | D42: 49440.46 | E42: 49849.84 | F42: 749.85 | G42: 1.53 | H42: 1.84 | I42: 1193.06 | J42: 34.79 | K42: 3.37 | L42: 0.72
A43: 44257 | B43: 50258.09 | C43: 50439.82 | D43: 49807.12 | E43: 50296.89 | F43: 447.05 | G43: 0.9 | H43: 1.75 | I43: 983.62 | J43: 35.12 | K43: 3.4 | L43: 0.71
A44: 44258 | B44: 50738.21 | C44: 51539.89 | D44: 50512.84 | E44: 51444.65 | F44: 1147.76 | G44: 2.28 | H44: 1.58 | I44: 1212.48 | J44: 36.07 | K44: 3.5 | L44: 0.69
A45: 44259 | B45: 50812.14 | C45: 51256.55 | D45: 50539.92 | E45: 50846.08 | F45: -598.57 | G45: -1.16 | H45: 2.18 | I45: 2139.25 | J45: 35.64 | K45: 3.45 | L45: 0.7
A46: 44260 | B46: 50517.36 | C46: 50886.19 | D46: 50160.54 | E46: 50405.32 | F46: -440.76 | G46: -0.87 | H46: 1.92 | I46: 1192.29 | J46: 35.12 | K46: 3.4 | L46: 0.71
A47: 44263 | B47: 50654.02 | C47: 50985.77 | D47: 50318.26 | E47: 50441.07 | F47: 35.75 | G47: 0.07 | H47: 1.42 | I47: 813.71 | J47: 35.09 | K47: 3.4 | L47: 0.71
A48: 44264 | B48: 50714.16 | C48: 51111.94 | D48: 50396.1 | E48: 51025.48 | F48: 584.41 | G48: 1.16 | H48: 1.22 | I48: 918.77 | J48: 35.65 | K48: 3.45 | L48: 0.7
A49: 44265 | B49: 51404.68 | C49: 51430.43 | D49: 51048.93 | E49: 51279.51 | F49: 254.03 | G49: 0.5 | H49: 0.93 | I49: 758.15 | J49: 35.94 | K49: 3.48 | L49: 0.7
A50: 44267 | B50: 51660.98 | C50: 51821.84 | D50: 50538.43 | E50: 50792.08 | F50: -487.43 | G50: -0.95 | H50: 1.22 | I50: 919.41 | J50: 35.36 | K50: 3.42 | L50: 0.71
... A53: 44272 | B53: 50436.02 | C53: 50561.12 | D53: 49718.65 | E53: 49801.62 | F53: -562.34 | G53: -1.12 | H53: 1.3 | I53: 793.3 | J53: 34.72 | K53: 3.36 | L53: 0.72
A54: 44273 | B54: 50161.25 | C54: 50296.35 | D54: 48962.36 | E54: 49216.52 | F54: -585.1 | G54: -1.17 | H54: - | J54: 34.32 | K54: 3.32 | L54: 0.73
A55: 44274 | B55: 48881.19 | C55: 50003.58 | D55: 48586.93 | E55: 49858.24 | F55: 641.72 | G55: 1.3 | H55: 1.75 | I55: 1227.79 | J55: 34.71 | K55: 3.36 | L55: 0.72
A56: 44277 | B56: 49878.77 | C56: 49878.77 | D56: 49281.02 | E56: 49771.29 | F56: -86.95 | G56: -0.17 | H56: 1.16 | I56: 800.22 | J56: 34.75 | K56: 3.37 | L56: 0.72
A57: 44278 | B57: 49876.21 | C57: 50264.65 | D57: 49661.92 | E57: 50051.44 | F57: 280.15 | G57: 0.56 | H57: 1.34 | I57: 940.53 | J57: 34.9 | K57: 3.38 | L57: 0.72
A58: 44279 | B58: 49786.47 | C58: 49854.58 | D58: 49120.34 | E58: 49180.31 | F58: -871.13 | G58: -1.74 | H58: 0.92 | I58: 698.04 | J58: 34.2 | K58: 3.31 | L58: 0.73
A59: 44280 | B59: 49201.98 | C59: 49247.95 | D59: 48236.35 | E59: 48440.12 | F59: -740.19 | G59: -1.51 | H59: 1.43 | I59: 938.59 | J59: 33.76 | K59: 3.27 | L59: 0.74
A60: 44281 | B60: 48969.25 | C60: 49234.66 | D60: 48699.91 | E60: 49008.5 | F60: 568.38 | G60: 1.17 | H60: 1.06 | I60: 889.41 | J60: 34.26 | K60: 3.32 | L60: 0.73
A61: 44285 | B61: 49331.68 | C61: 50268.45 | D61: 49331.68 | E61: 50136.58 | F61: 1128.08 | G61: 2.3 | H61: 1.05 | I61: 887.83 | J61: 34.59 | K61: 3.35 | L61: 0.72
A62: 44286 | B62: 50049.12 | C62: 50050.32 | D62: 49442.5 | E62: 49509.15 | F62: -627.43 | G62: -1.25 | H62: 1.19 | I62: 808.09 | J62: 34.36 | K62: 3.33 | L62: 0.73
A63: 44287 | B63: 49868.53 | C63: 50092.48 | D63: 49478.53 | E63: 50029.83 | F63: 520.68 | G63: 1.05 | H63: 0.85 | I63: 677.76 | J63: 34.84 | K63: 3.38 | L63: 0.72
A64: 44291 | B64: 50020.91 | C64: 50028.67 | D64: 48580.8 | E64: 49159.32 | F64: -870.51 | G64: -1.74 | H64: 1.27 | I64: 1226.04 | J64: 34.25 | K64: 3.32 | L64: 0.73
A65: 44292 | B65: 49441.13 | C65: 49582.26 | D65: 48936.35 | E65: 49201.39 | F65: 42.07 | G65: 0.09 | H65: - | J65: 34.26 | K65: 3.32 | L65: 0.73
A66: 44293 | B66: 49277.09 | C66: 49900.13 | D66: 49093.9 | E66: 49661.76 | F66: 460.37 | G66: 0.94 | H66: 0.98 | I66: 768.54 | J66: 34.08 | K66: 3.3 | L66: 0.73
A67: 44294 | B67: 49885.26 | C67: 50118.08 | D67: 49581.61 | E67: 49746.21 | F67: 84.45 | G67: 0.17 | H67: 2.18 | I67: 2020 | J67: 34.04 | K67: 3.3 | L67: 0.73
A68: 44295 | B68: 49743.39 | C68: 49906.91 | D68: 49461.01 | E68: 49591.32 | F68: -154.89 | G68: -0.31 | H68: 0.89 | I68: 764.61 | J68: 34.29 | K68: 3.33 | L68: 0.73
A69: 44298 | B69: 48956.65 | C69: 48956.65 | D69: 47693.44 | E69: 47883.38 | F69: -1707.94 | G69: -3.44 | H69: 1.91 | I69: 1433.61 | J69: 33.15 | K69: 3.22 | L69: 0.75
A70: 44299 | B70: 47991.53 | C70: 48627.43 | D70: 47775.32 | E70: 48544.06 | F70: 660.68 | G70: 1.38 | H70: 1 | I70: 884.9 | J70: 33.42 | K70: 3.24 | L70: 0.74
A71: 44301 | B71: 48512.77 | C71: 48887.85 | D71: 48010.55 | E71: 48803.68 | F71: 259.62 | G71: 0.53 | H71: 1.61 | I71: 1606.86 | J71: 33.9 | K71: 3.3 | L71: 0.74
A72: 44302 | B72: 48935.74 | C72: 49089.55 | D72: 48694.49 | E72: 48832.03 | F72: 28.35 | G72: 0.06 | H72: 1.19 | I72: 1163.86 | J72: 33.95 | K72: 3.31 | L72: 0.74
A73: 44305 | B73: 47940.81 | C73: 48020.79 | D73: 47362.71 | E73: 47949.42 | F73: -882.61 | G73: -1.81 | H73: 1.05 | I73: 912.93 | J73: 32.79 | K73: 3.2 | L73: 0.82
A74: 44306 | B74: 48473.04 | C74: 48478.34 | D74: 47438.5 | E74: 47705.8 | F74: -243.62 | G74: -0.51 | H74: 1.16 | I74: 990.42 | J74: 32.59 | K74: 3.18 | L74: 0.83
A75: 44308 | B75: 47501.71 | C75: 48143.16 | D75: 47204.5 | E75: 48080.67 | F75: 374.87 | G75: 0.79 | H75: 1.58 | I75: 1433.32 | J75: 33.12 | K75: 3.23 | L75: 0.81
A76: 44309 | B76: 47863.81 | C76: 48265.39 | D76: 47669.55 | E76: 47878.45 | F76: -202.22 | G76: -0.42 | H76: 1.12 | I76: 890.23 | J76: 32.94 | K76: 3.21 | L76: 0.82
A77: 44312 | B77: 48197.37 | C77: 48667.98 | D77: 48152.24 | E77: 48386.51 | F77: 508.06 | G77: 1.06 | H77: 1.52 | I77: 1199.52 | J77: 33.26 | K77: 3.24 | L77: 0.81
A78: 44313 | B78: 48424.08 | C78: 49009.26 | D78: 48399.53 | E78: 48944.14 | F78: 557.63 | G78: 1.15 | H78: - | J78: 32.96 | K78: 3.27 | L78: 0.8
A79: 44314 | B79: 49066.64 | C79: 49801.48 | D79: 49066.64 | E79: 49733.84 | F79: 789.7 | G79: 1.61 | H79: - | J79: 33.59 | K79: 3.33 | L79: 0.81
A80: 44315 | B80: 50093.86 | C80: 50375.77 | D80: 49535.98 | E80: 49765.94 | F80: 32.1 | G80: 0.06 | H80: 0.9 | I80: 714.46 | J80: 32.9 | K80: 3.33 | L80: 0.8
A81: 44316 | B81: 49360.89 | C81: 49569.42 | D81: 48698.08 | E81: 48782.36 | F81: -983.58 | G81: -1.98 | H81: - | J81: 32.1 | K81: 3.25 | L81: 0.82
A82: 44319 | B82: 48356.01 | C82: 48863.23 | D82: 48028.07 | E82: 48718.52 | F82: -63.84 | G82: -0.13 | H82: 1.47 | I82: 1109.65 | J82: 31.12 | K82: 3.15 | L82: 0.85
A83: 44320 | B83: 48881.63 | C83: 48996.53 | D83: 48149.45 | E83: 48253.51 | F83: -465.01 | G83: -0.95 | H83: 1.32 | I83: 1107.69 | J83: 30.88 | K83: 3.12 | L83: 0.86
A84: 44321 | B84: 48569.12 | C84: 48742.72 | D84: 48254.32 | E84: 48677.55 | F84: 424.04 | G84: 0.88 | H84: 1.27 | I84: 840.95 | J84: 30.92 | K84: 3.13 | L84: 0.86
A85: 44322 | B85: 48877.78 | C85: 49011.31 | D85: 48614.11 | E85: 48949.76 | F85: 272.21 | G85: 0.56 | H85: 0.95 | I85: 710.88 | J85: 31.13 | K85: 3.15 | L85: 0.85
A86: 44323 | B86: 49169.14 | C86: 49417.64 | D86: 49036.38 | E86: 49206.47 | F86: 256.71 | G86: 0.52 | H86: - | J86: 31.41 | K86: 3.18 | L86: 0.84
A87: 44326 | B87: 49496.05 | C87: 49617.47 | D87: 49412.05 | E87: 49502.41 | F87: 295.94 | G87: 0.6 | H87: 1.22 | I87: 738.57 | J87: 31.48 | K87: 3.18 | L87: 0.85
A88: 44327 | B88: 49066.45 | C88: 49304.47 | D88: 48988.18 | E88: 49161.81 | F88: -340.6 | G88: -0.69 | H88: 1.5 | I88: 775.45 | J88: 31.16 | K88: 3.14 | L88: 0.86
A89: 44328 | B89: 49171.28 | C89: 49171.28 | D89: 48550.72 | E89: 48690.8 | F89: -471.01 | G89: -0.96 | H89: - | J89: 30.88 | K89: 3.11 | L89: 0.87
A90: 44330 | B90: 48898.93 | C90: 48898.93 | D90: 48473.43 | E90: 48732.55 | F90: 41.75 | G90: 0.09 | H90: 1.82 | I90: 1215.23 | J90: 31.03 | K90: 3.13 | L90: 0.87
A91: 44333 | B91: 48990.7 | C91: 49628.42 | D91: 48923.13 | E91: 49580.73 | F91: 848.18 | G91: 1.74 | H91: 2.06 | I91: 1284.48 | J91: 31.43 | K91: 3.17 | L91: 0.86
A92: 44334 | B92: 49986.68 | C92: 50313.25 | D92: 49959.2 | E92: 50193.33 | F92: 612.6 | G92: 1.24 | H92: 1.44 | I92: 1016.52 | J92: 31.9 | K92: 3.21 | L92: 0.85
A93: 44335 | B93: 50088.81 | C93: 50279.01 | D93: 49831.4 | E93: 49902.64 | F93: -290.69 | G93: -0.58 | H93: - | J93: 31.69 | K93: 3.19 | L93: 0.85
A94: 44336 | B94: 49971.52 | C94: 50099.17 | D94: 49496.78 | E94: 49564.86 | F94: -337.78 | G94: -0.68 | H94: 0.83 | I94: 633.93 | J94: 30.83 | K94: 3.16 | L94: 0.86
A95: 44337 | B95: 49833.98 | C95: 50591.12 | D95: 49832.72 | E95: 50540.48 | F95: 975.62 | G95: 1.97 | H95: - | J95: 31.57 | K95: 3.23 | L95: 0.85
A96: 44340 | B96: 50727.28 | C96: 50857.59 | D96: 50465.9 | E96: 50651.9 | F96: 111.42 | G96: 0.22 | H96: 1.68 | I96: 1167.45 | J96: 31.51 | K96: 3.23 | L96: 0.87
A97: 44341 | B97: 50922.32 | C97: 50961.35 | D97: 50474.34 | E97: 50637.53 | F97: -14.37 | G97: -0.03 | H97: - | J97: 31.56 | K97: 3.23 | L97: 0.87
A98: 44342 | B98: 50899.58 | C98: 51072.61 | D98: 50620.45 | E98: 51017.52 | F98: 379.99 | G98: 0.75 | H98: - | J98: 31.62 | K98: 3.26 | L98: 0.86
A99: 44343 | B99: 51128.8 | C99: 51282.9 | D99: 50891.66 | E99: 51115.22 | F99: 97.7 | G99: 0.19 | H99: 1.23 | I99: 976.34 | J99: 31.69 | K99: 3.27 | L99: 0.86
A100: 44344 | B100: 51381.27 | C100: 51529.32 | D100: 51258.69 | E100: 51422.88 | F100: 307.66 | G100: 0.6 | H100: 2.31 | I100: 2134.47 | J100: 31.9 | K100: 3.29 | L100: 0.85
A101: 44347 | B101: 51476.22 | C101: 52013.22 | D101: 51179.94 | E101: 51937.44 | F101: 514.56 | G101: 1 | H101: 1.53 | I101: 1386.77 | J101: 31.33 | K101: 3.3 | L101: 0.86
A102: 44348 | B102: 52067.51 | C102: 52228.65 | D102: 51808.88 | E102: 51934.88 | F102: -2.56 | G102: 0 | H102: - | J102: 31.23 | K102: 3.28 | L102: 0.86
A103: 44349 | B103: 51749.1 | C103: 51913.92 | D103: 51450.58 | E103: 51849.48 | F103: -85.4 | G103: -0.16 | H103: - | J103: 31.15 | K103: 3.28 | L103: 0.87
A104: 44350 | B104: 52121.58 | C104: 52273.23 | D104: 51942.2 | E104: 52232.43 | F104: 382.95 | G104: 0.74 | H104: 1.17 | I104: 691.22 | J104: 31.56 | K104: 3.32 | L104: 0.96
A105: 44351 | B105: 52367.52 | C105: 52389.02 | D105: 51952.7 | E105: 52100.05 | F105: -132.38 | G105: -0.25 | H105: 1.67 | I105: 1144.01 | J105: 31.47 | K105: 3.31 | L105: 0.96
...

Sheet Stock Returns
A1: Date | B1: Close Price | C1: Daily Stock Returns | D1: Daily Stock Returns% | O1: Date | P1: Close Price | Q1: Daily Market Returns | R1: Daily Market Returns%
A2: 44197 | B2: 33.1 | C2: - | D2: - | O2: 44197 | P2: 47868.98 | Q2: -
A3: 44200 | B3: 32.2 | C3: =(B3-B2)/B2 -> -0.027190332 | D3: =(B3-B2)/B2 -> -0.027190332 | O3: 44200 | P3: 48176.8 | Q3: =(P3-P2)/P2 -> 0.0064304692 | R3: =(P3-P2)/P2 -> 0.0064304692 | U3: Returns | V3: Returns%
A4: 44201 | B4: 31.95 | C4: =(B4-B3)/B3 -> -0.0077639752 | D4: =(B4-B3)/B3 -> -0.0077639752 | F4: Returns | G4: Returns% | O4: 44201 | P4: 48437.78 | Q4: =(P4-P3)/P3 -> 0.0054171302 | R4: =(P4-P3)/P3 -> 0.0054171302 | T4: Average Daily Market Returns | U4: =AVERAGE(Q3:Q1241) -> 0.00050461517 | V4: =AVERAGE(Q3:Q1241) -> 0.00050461517
A5: 44202 | B5: 30.9 | C5: =(B5-B4)/B4 -> -0.03286385 | D5: =(B5-B4)/B4 -> -0.03286385 | E5: Average Daily Stock Returns | F5: =AVERAGE(C3:C1241) -> 0.0026696663 | G5: =AVERAGE(C3:C1241) -> 0.0026696663 | O5: 44202 | P5: 48174.06 | Q5: =(P5-P4)/P4 -> -0.0054445105 | R5: =(P5-P4)/P4 -> -0.0054445105 | T5: Standard Deviation of daily Market Returns | U5: =_xlfn.STDEV.S(Q3:Q1241) -> 0.0088282244 | V5: =_xlfn.STDEV.S(Q3:Q1241) -> 0.0088282244
A6: 44203 | B6: 33.9 | C6: =(B6-B5)/B5 -> 0.097087379 | D6: =(B6-B5)/B5 -> 0.097087379 | E6: Standard Deviation of daily Stock Returns | F6: =_xlfn.STDEV.S(C3:C1241) -> 0.039014628 | G6: =_xlfn.STDEV.S(C3:C1241) -> 0.039014628 | O6: 44203 | P6: 48093.32 | Q6: =(P6-P5)/P5 -> -0.0016760057 | R6: =(P6-P5)/P5 -> -0.0016760057 | Y6: Covariance between the stock returns and market returns | Z6: =_xlfn.COVARIANCE.S(C3:C1241,Q3:Q1241) -> 7.329155e-05
A7: 44204 | B7: 33.05 | C7: =(B7-B6)/B6 -> -0.025073746 | D7: =(B7-B6)/B6 -> -0.025073746 | O7: 44204 | P7: 48782.51 | Q7: =(P7-P6)/P6 -> 0.014330265 | R7: =(P7-P6)/P6 -> 0.014330265 | Y7: Correlation coefficient between the stock returns and market returns | Z7: =CORREL(C3:C1241,Q3:Q1241) -> 0.21279091
A8: 44207 | B8: 32.85 | C8: =(B8-B7)/B7 -> -0.0060514372 | D8: =(B8-B7)/B7 -> -0.0060514372 | O8: 44207 | P8: 49269.32 | Q8: =(P8-P7)/P7 -> 0.0099791913 | R8: =(P8-P7)/P7 -> 0.0099791913 | T8: Market Return | U8: Daily Market Return | V8: Annualized Daily Return
A9: 44208 | B9: 32.05 | C9: =(B9-B8)/B8 -> -0.02435312 | D9: =(B9-B8)/B8 -> -0.02435312 | H9: Stock Return | I9: Daiy Stock Return | J9: Annualized daily Return | O9: 44208 | P9: 49517.11 | Q9: =(P9-P8)/P8 -> 0.0050292961 | R9: =(P9-P8)/P8 -> 0.0050292961 | T9: year1 01-01-21 to 31-12-21 | U9: =AVERAGE(Q3:Q249) -> 0.00084485719 | V9: =(1+U9)^252-1 -> 0.23715467
A10: 44209 | B10: 31.2 | C10: =(B10-B9)/B9 -> -0.026521061 | D10: =(B10-B9)/B9 -> -0.026521061 | H10: year1 01-01-21 to 31-12-21 | I10: =AVERAGE(C3:C249) -> 0.0046625504 | J10: =(1+I10)^252-1 -> 2.2291922 | O10: 44209 | P10: 49492.32 | Q10: =(P10-P9)/P9 -> -0.00050063503 | R10: =(P10-P9)/P9 -> -0.00050063503 | T10: year 2 01-01-22 to 31-12-22 | U10: =AVERAGE(Q250:Q497) -> 0.00023578935 | V10: =(1+U10)^252-1 -> 0.061212276 | AO10: E(Ri​) = Expected return of the company
A11: 44210 | B11: 29.75 | C11: =(B11-B10)/B10 -> -0.046474359 | D11: =(B11-B10)/B10 -> -0.046474359 | H11: year 2 01-01-22 to 31-12-22 | I11: =AVERAGE(C250:C497) -> 0.003715865 | J11: =(1+I11)^252-1 -> 1.5463539 | O11: 44210 | P11: 49584.16 | Q11: =(P11-P10)/P10 -> 0.0018556414 | R11: =(P11-P10)/P10 -> 0.0018556414 | T11: year 3 01-01-23 to 31-12-23 | U11: =AVERAGE(Q498:Q743) -> 0.00071776648 | V11: =(1+U11)^252-1 -> 0.19819022 | AO11: Rf​ = Risk-free rate = 6.72%
A12: 44211 | B12: 29.25 | C12: =(B12-B11)/B11 -> -0.016806723 | D12: =(B12-B11)/B11 -> -0.016806723 | H12: year 3 01-01-23 to 31-12-23 | I12: =AVERAGE(C498:C743) -> 0.0039596794 | J12: =(1+I12)^252-1 -> 1.7070753 | O12: 44211 | P12: 49034.67 | Q12: =(P12-P11)/P11 -> -0.011081966 | R12: =(P12-P11)/P11 -> -0.011081966 | T12: year 4 01-01-24 to 31-12-24 | U12: =AVERAGE(Q744:Q992) -> 0.00035357753 | V12: =(1+U12)^252-1 -> 0.093174435 | AI12: E(Ri​)=Rf​+βi​(Rm​−Rf​)​ | AL12: Rf​ = Risk-free rate = 6.72% | AO12: βi​ = Beta of the company
A13: 44214 | B13: 29.1 | C13: =(B13-B12)/B12 -> -0.0051282051 | D13: =(B13-B12)/B12 -> -0.0051282051 | H13: year 4 01-01-24 to 31-12-24 | I13: =AVERAGE(C744:C992) -> 0.0038448172 | J13: =(1+I13)^252-1 -> 1.6301374 | O13: 44214 | P13: 48564.27 | Q13: =(P13-P12)/P12 -> -0.0095932123 | R13: =(P13-P12)/P12 -> -0.0095932123 | T13: year 5 01-01-25 to 31-12-25 | U13: =AVERAGE(Q993:Q1241) -> 0.00037530667 | V13: =(1+U13)^252-1 -> 0.099174603 | AN13: 0.0672 | AO13: Rm​ = Annual market return
A14: 44215 | B14: 30.2 | C14: =(B14-B13)/B13 -> 0.037800687 | D14: =(B14-B13)/B13 -> 0.037800687 | H14: year 5 01-01-25 to 31-12-25 | I14: =AVERAGE(C994:C1242) -> -0.0028500384 | J14: =(1+I14)^252-1 -> -0.51287528 | O14: 44215 | P14: 49398.29 | Q14: =(P14-P13)/P13 -> 0.017173531 | R14: =(P14-P13)/P13 -> 0.017173531
A15: 44216 | B15: 30.15 | C15: =(B15-B14)/B14 -> -0.0016556291 | D15: =(B15-B14)/B14 -> -0.0016556291 | O15: 44216 | P15: 49792.12 | Q15: =(P15-P14)/P14 -> 0.0079725432 | R15: =(P15-P14)/P14 -> 0.0079725432 | AO15: E(Ri​)=Rf​+βi​(Rm​−Rf​)​
A16: 44217 | B16: 29 | C16: =(B16-B15)/B15 -> -0.03814262 | D16: =(B16-B15)/B15 -> -0.03814262 | O16: 44217 | P16: 49624.76 | Q16: =(P16-P15)/P15 -> -0.0033611744 | R16: =(P16-P15)/P15 -> -0.0033611744 | AI16: Years | AJ16: Beta | AK16: Interpretation | AM16: Annualized Market Return | AO16: Annualized Stock Return | AQ16: CAPM Expected | AR16: Interpretation
A17: 44218 | B17: 27.8 | C17: =(B17-B16)/B16 -> -0.04137931 | D17: =(B17-B16)/B16 -> -0.04137931 | O17: 44218 | P17: 48878.54 | Q17: =(P17-P16)/P16 -> -0.015037252 | R17: =(P17-P16)/P16 -> -0.015037252 | AI17: 2021 | AJ17: =_xlfn.COVARIANCE.S(C3:C249,Q3:Q249)/_xlfn.VAR.S(Q3:Q249) -> 0.59135391 | AK17: Lower market sensitivity | AM17: =V9 -> 0.23715467 | AO17: =J10 -> 2.2291922 | AQ17: =$AN$13 + AJ17 * (AM17 - $AN$13) -> 0.16770336 | AR17: Above
A18: 44221 | B18: 27.05 | C18: =(B18-B17)/B17 -> -0.026978417 | D18: =(B18-B17)/B17 -> -0.026978417 | O18: 44221 | P18: 48347.59 | Q18: =(P18-P17)/P17 -> -0.01086264 | R18: =(P18-P17)/P17 -> -0.01086264 | AI18: 2022 | AJ18: =_xlfn.COVARIANCE.S(C250:C497,Q250:Q497)/_xlfn.VAR.S(Q250:Q497) -> 0.85889437 | AK18: Lower market sensitivity | AM18: =V10 -> 0.061212276 | AO18: =J11 -> 1.5463539 | AQ18: =$AN$13 + AJ18 * (AM18 - $AN$13) -> 0.062057177 | AR18: Above
A19: 44223 | B19: 28.35 | C19: =(B19-B18)/B18 -> 0.04805915 | D19: =(B19-B18)/B18 -> 0.04805915 | O19: 44223 | P19: 47409.93 | Q19: =(P19-P18)/P18 -> -0.019394141 | R19: =(P19-P18)/P18 -> -0.019394141 | AI19: 2023 | AJ19: =_xlfn.COVARIANCE.S(C498:C743,Q498:Q743)/_xlfn.VAR.S(Q498:Q743) -> 0.73274519 | AK19: Lower market sensitivity | AM19: =V11 -> 0.19819022 | AO19: =J12 -> 1.7070753 | AQ19: =$AN$13 + AJ19 * (AM19 - $AN$13) -> 0.16318245 | AR19: Above
A20: 44224 | B20: 27.65 | C20: =(B20-B19)/B19 -> -0.024691358 | D20: =(B20-B19)/B19 -> -0.024691358 | O20: 44224 | P20: 46874.36 | Q20: =(P20-P19)/P19 -> -0.011296579 | R20: =(P20-P19)/P19 -> -0.011296579 | AI20: 2024 | AJ20: =_xlfn.COVARIANCE.S(C744:C992,Q744:Q992)/_xlfn.VAR.S(Q744:Q992) -> 1.0117773 | AK20: Approximately same sensitivity as market | AM20: =V12 -> 0.093174435 | AO20: =J13 -> 1.6301374 | AQ20: =$AN$13 + AJ20 * (AM20 - $AN$13) -> 0.093480344 | AR20: Above
A21: 44225 | B21: 28.1 | C21: =(B21-B20)/B20 -> 0.016274864 | D21: =(B21-B20)/B20 -> 0.016274864 | O21: 44225 | P21: 46285.77 | Q21: =(P21-P20)/P20 -> -0.012556758 | R21: =(P21-P20)/P20 -> -0.012556758 | AI21: 2025 | AJ21: =_xlfn.COVARIANCE.S(C993:C1241,Q993:Q1241)/_xlfn.VAR.S(Q993:Q1241) -> 1.7914054 | AK21: Much higher market sensitivity | AM21: =V13 -> 0.099174603 | AO21: =J14 -> -0.51287528 | AQ21: =$AN$13 + AJ21 * (AM21 - $AN$13) -> 0.12447948 | AR21: Below
A22: 44228 | B22: 28.2 | C22: =(B22-B21)/B21 -> 0.0035587189 | D22: =(B22-B21)/B21 -> 0.0035587189 | O22: 44228 | P22: 48600.61 | Q22: =(P22-P21)/P21 -> 0.050011915 | R22: =(P22-P21)/P21 -> 0.050011915
A23: 44229 | B23: 28.2 | C23: =(B23-B22)/B22 -> 0 | D23: =(B23-B22)/B22 -> 0 | O23: 44229 | P23: 49797.72 | Q23: =(P23-P22)/P22 -> 0.024631584 | R23: =(P23-P22)/P22 -> 0.024631584
A24: 44230 | B24: 27.95 | C24: =(B24-B23)/B23 -> -0.0088652482 | D24: =(B24-B23)/B23 -> -0.0088652482 | O24: 44230 | P24: 50255.75 | Q24: =(P24-P23)/P23 -> 0.0091978107 | R24: =(P24-P23)/P23 -> 0.0091978107
A25: 44231 | B25: 28.5 | C25: =(B25-B24)/B24 -> 0.019677996 | D25: =(B25-B24)/B24 -> 0.019677996 | O25: 44231 | P25: 50614.29 | Q25: =(P25-P24)/P24 -> 0.007134308 | R25: =(P25-P24)/P24 -> 0.007134308
A26: 44232 | B26: 28.3 | C26: =(B26-B25)/B25 -> -0.0070175439 | D26: =(B26-B25)/B25 -> -0.0070175439 | O26: 44232 | P26: 50731.63 | Q26: =(P26-P25)/P25 -> 0.0023183176 | R26: =(P26-P25)/P25 -> 0.0023183176
A27: 44235 | B27: 30.25 | C27: =(B27-B26)/B26 -> 0.068904594 | D27: =(B27-B26)/B26 -> 0.068904594 | O27: 44235 | P27: 51348.77 | Q27: =(P27-P26)/P26 -> 0.012164797 | R27: =(P27-P26)/P26 -> 0.012164797
A28: 44236 | B28: 30.25 | C28: =(B28-B27)/B27 -> 0 | D28: =(B28-B27)/B27 -> 0 | O28: 44236 | P28: 51329.08 | Q28: =(P28-P27)/P27 -> -0.00038345612 | R28: =(P28-P27)/P27 -> -0.00038345612
A29: 44237 | B29: 28.8 | C29: =(B29-B28)/B28 -> -0.047933884 | D29: =(B29-B28)/B28 -> -0.047933884 | O29: 44237 | P29: 51309.39 | Q29: =(P29-P28)/P28 -> -0.00038360321 | R29: =(P29-P28)/P28 -> -0.00038360321
A30: 44238 | B30: 29.9 | C30: =(B30-B29)/B29 -> 0.038194444 | D30: =(B30-B29)/B29 -> 0.038194444 | O30: 44238 | P30: 51531.52 | Q30: =(P30-P29)/P29 -> 0.0043292271 | R30: =(P30-P29)/P29 -> 0.0043292271
A31: 44239 | B31: 29.65 | C31: =(B31-B30)/B30 -> -0.008361204 | D31: =(B31-B30)/B30 -> -0.008361204 | O31: 44239 | P31: 51544.3 | Q31: =(P31-P30)/P30 -> 0.00024800355 | R31: =(P31-P30)/P30 -> 0.00024800355
A32: 44242 | B32: 27.25 | C32: =(B32-B31)/B31 -> -0.080944351 | D32: =(B32-B31)/B31 -> -0.080944351 | O32: 44242 | P32: 52154.13 | Q32: =(P32-P31)/P31 -> 0.011831182 | R32: =(P32-P31)/P31 -> 0.011831182
A33: 44243 | B33: 26.45 | C33: =(B33-B32)/B32 -> -0.029357798 | D33: =(B33-B32)/B32 -> -0.029357798 | O33: 44243 | P33: 52104.17 | Q33: =(P33-P32)/P32 -> -0.00095792989 | R33: =(P33-P32)/P32 -> -0.00095792989
... A1241: 46022 | B1241: 334 | C1241: =(B1241-B1240)/B1240 -> -0.0028362442 | D1241: =(B1241-B1240)/B1240 -> -0.0028362442 | O1241: 46022 | P1241: 85220.6 | Q1241: =(P1241-P1240)/P1240 -> 0.0064425094 | R1241: =(P1241-P1240)/P1240 -> 0.0064425094

Sheet Market Returns 
A1: Date | B1: Close Price | C1: Daily Market Returns | D1: Daily Market Returns%
A2: 44197 | B2: 47868.98 | C2: -
A3: 44200 | B3: 48176.8 | C3: =(B3-B2)/B2 -> 0.0064304692 | D3: =(B3-B2)/B2 -> 0.0064304692 | G3: Returns | H3: Returns%
A4: 44201 | B4: 48437.78 | C4: =(B4-B3)/B3 -> 0.0054171302 | D4: =(B4-B3)/B3 -> 0.0054171302 | F4: Average Daily Market Returns | G4: =AVERAGE(C3:C1241) -> 0.00050461517 | H4: =AVERAGE(C3:C1241) -> 0.00050461517
A5: 44202 | B5: 48174.06 | C5: =(B5-B4)/B4 -> -0.0054445105 | D5: =(B5-B4)/B4 -> -0.0054445105 | F5: Standard Deviation of daily Market Returns | G5: =_xlfn.STDEV.S(C3:C1241) -> 0.0088282244 | H5: =_xlfn.STDEV.S(C3:C1241) -> 0.0088282244
A6: 44203 | B6: 48093.32 | C6: =(B6-B5)/B5 -> -0.0016760057 | D6: =(B6-B5)/B5 -> -0.0016760057
A7: 44204 | B7: 48782.51 | C7: =(B7-B6)/B6 -> 0.014330265 | D7: =(B7-B6)/B6 -> 0.014330265
A8: 44207 | B8: 49269.32 | C8: =(B8-B7)/B7 -> 0.0099791913 | D8: =(B8-B7)/B7 -> 0.0099791913 | F8: Market Return | G8: Daily Market Return | H8: Annualized Daily Return
A9: 44208 | B9: 49517.11 | C9: =(B9-B8)/B8 -> 0.0050292961 | D9: =(B9-B8)/B8 -> 0.0050292961 | F9: year1 01-01-21 to 31-12-21 | G9: =AVERAGE(C3:C249) -> 0.00084485719 | H9: =(1+G9)^252-1 -> 0.23715467
A10: 44209 | B10: 49492.32 | C10: =(B10-B9)/B9 -> -0.00050063503 | D10: =(B10-B9)/B9 -> -0.00050063503 | F10: year 2 01-01-22 to 31-12-22 | G10: =AVERAGE(C250:C497) -> 0.00023578935 | H10: =(1+G10)^252-1 -> 0.061212276
A11: 44210 | B11: 49584.16 | C11: =(B11-B10)/B10 -> 0.0018556414 | D11: =(B11-B10)/B10 -> 0.0018556414 | F11: year 3 01-01-23 to 31-12-23 | G11: =AVERAGE(C498:C743) -> 0.00071776648 | H11: =(1+G11)^252-1 -> 0.19819022
A12: 44211 | B12: 49034.67 | C12: =(B12-B11)/B11 -> -0.011081966 | D12: =(B12-B11)/B11 -> -0.011081966 | F12: year 4 01-01-24 to 31-12-24 | G12: =AVERAGE(C744:C992) -> 0.00035357753 | H12: =(1+G12)^252-1 -> 0.093174435
A13: 44214 | B13: 48564.27 | C13: =(B13-B12)/B12 -> -0.0095932123 | D13: =(B13-B12)/B12 -> -0.0095932123 | F13: year 5 01-01-25 to 31-12-25 | G13: =AVERAGE(C993:C1241) -> 0.00037530667 | H13: =(1+G13)^252-1 -> 0.099174603
A14: 44215 | B14: 49398.29 | C14: =(B14-B13)/B13 -> 0.017173531 | D14: =(B14-B13)/B13 -> 0.017173531
A15: 44216 | B15: 49792.12 | C15: =(B15-B14)/B14 -> 0.0079725432 | D15: =(B15-B14)/B14 -> 0.0079725432
A16: 44217 | B16: 49624.76 | C16: =(B16-B15)/B15 -> -0.0033611744 | D16: =(B16-B15)/B15 -> -0.0033611744
A17: 44218 | B17: 48878.54 | C17: =(B17-B16)/B16 -> -0.015037252 | D17: =(B17-B16)/B16 -> -0.015037252
A18: 44221 | B18: 48347.59 | C18: =(B18-B17)/B17 -> -0.01086264 | D18: =(B18-B17)/B17 -> -0.01086264
A19: 44223 | B19: 47409.93 | C19: =(B19-B18)/B18 -> -0.019394141 | D19: =(B19-B18)/B18 -> -0.019394141
A20: 44224 | B20: 46874.36 | C20: =(B20-B19)/B19 -> -0.011296579 | D20: =(B20-B19)/B19 -> -0.011296579
A21: 44225 | B21: 46285.77 | C21: =(B21-B20)/B20 -> -0.012556758 | D21: =(B21-B20)/B20 -> -0.012556758
A22: 44228 | B22: 48600.61 | C22: =(B22-B21)/B21 -> 0.050011915 | D22: =(B22-B21)/B21 -> 0.050011915
A23: 44229 | B23: 49797.72 | C23: =(B23-B22)/B22 -> 0.024631584 | D23: =(B23-B22)/B22 -> 0.024631584
A24: 44230 | B24: 50255.75 | C24: =(B24-B23)/B23 -> 0.0091978107 | D24: =(B24-B23)/B23 -> 0.0091978107
A25: 44231 | B25: 50614.29 | C25: =(B25-B24)/B24 -> 0.007134308 | D25: =(B25-B24)/B24 -> 0.007134308
... A1241: 46022 | B1241: 85220.6 | C1241: =(B1241-B1240)/B1240 -> 0.0064425094 | D1241: =(B1241-B1240)/B1240 -> 0.0064425094

Sheet Coveriance and Correlation
A1: Covariance between the stock returns and market returns | B1: =_xlfn.COVARIANCE.S('Stock Returns'!C3:C1241,'Market Returns '!C3:C1241) -> 7.329155e-05
A2: Correlation coefficient between the stock returns and market returns | B2: =CORREL('Stock Returns'!C3:C1241,'Market Returns '!C3:C1241) -> 0.21279091

Sheet Beta
A1: 5 Year Beta | B1: =_xlfn.COVARIANCE.S('Stock Returns'!C3:C1241,'Market Returns '!C3:C1241)/_xlfn.VAR.S('Market Returns '!C3:C1241) -> 0.94038821 | D1: βi​ - | E1: COVARIANCE.S(Company_Returns,Market_Returns)/VAR.S(Market_Returns) | M1: For 5 years
A3: This means Dynamic Cables Ltd. has slightly lower systematic risk than the market.
A5: β = 1 → moves approximately in line with the market
A6: β > 1 → more sensitive/risky than the market
A7: β < 1 → less sensitive than the market
A8: β = 0.94 → if the market moves by 1%, Dynamic Cables would theoretically be expected to move by about 0.94% in the same direction, on average.
A10: So we can say that:
A12: Dynamic Cables Ltd. has a beta of approximately 0.94, indicating that the stock has slightly lower systematic risk than the market. movements is slightly lower.
A13: The stock tends to move in the same direction as the market, but its sensitivity to market

Sheet 5 years Beta
A1: E(Ri​)=Rf​+βi​(Rm​−Rf​)​ | D1: Rf​ = Risk-free rate = 6.72%
A5: Years | B5: Beta | C5: Interpretation | G5: Annualized Market Return | I5: Annualized Stock Return
A6: 2021 | B6: =_xlfn.COVARIANCE.S('Stock Returns'!C3:C249,'Market Returns '!C3:C249)/_xlfn.VAR.S('Market Returns '!C3:C249) -> 0.59135391 | C6: Lower market sensitivity | G6: ='Market Returns '!H9 -> 0.23715467 | I6: ='Stock Returns'!J10 -> 2.2291922
A7: 2022 | B7: =CAPM!B19 -> 0.85889437 | C7: Lower market sensitivity | G7: ='Market Returns '!H10 -> 0.061212276 | I7: ='Stock Returns'!J11 -> 1.5463539
A8: 2023 | B8: =CAPM!B20 -> 0.73274519 | C8: Lower market sensitivity | G8: ='Market Returns '!H11 -> 0.19819022 | I8: ='Stock Returns'!J12 -> 1.7070753
A9: 2024 | B9: =_xlfn.COVARIANCE.S('Stock Returns'!C744:C992,'Market Returns '!C744:C992)/_xlfn.VAR.S('Market Returns '!C744:C992) -> 1.0117773 | C9: Approximately same sensitivity as market | G9: ='Market Returns '!H12 -> 0.093174435 | I9: ='Stock Returns'!J13 -> 1.6301374
A10: 2025 | B10: =_xlfn.COVARIANCE.S('Stock Returns'!C993:C1241,'Market Returns '!C993:C1241)/_xlfn.VAR.S('Market Returns '!C993:C1241) -> 1.7914054 | C10: Much higher market sensitivity | G10: ='Market Returns '!H13 -> 0.099174603 | I10: ='Stock Returns'!J14 -> -0.51287528

Sheet CAPM
F1: E(Ri​) = Expected return of the company
F2: Rf​ = Risk-free rate = 6.72%
F3: βi​ = Beta of the company
F4: Rm​ = Annual market return
A5: 1. Capital Asset Pricing Model (CAPM) With 5 year Beta | D5: 0.0672
A7: E(Ri​)=Rf​+βi​(Rm​−Rf​)​
A16: Capital Asset Pricing Model (CAPM) With Per year Beta for 5 years
A17: Year | B17: Beta | C17: Annualized Stock Return | E17: Annualized Market Return | F17: Annualized Market Return % | H17: CAPM Expected | I17: Interpretation
A18: Year 1 | B18: =_xlfn.COVARIANCE.S('Stock Returns'!C3:C249,'Market Returns '!C3:C249)/_xlfn.VAR.S('Market Returns '!C3:C249) -> 0.59135391 | C18: ='Stock Returns'!J10 -> 2.2291922 | E18: ='Market Returns '!H9 -> 0.23715467 | F18: =E18 -> 0.23715467 | H18: =$D$5+B18*(CAPM!E18-CAPM!D5) -> 0.16770336 | I18: Above
A19: Year 2 | B19: =_xlfn.COVARIANCE.S('Stock Returns'!C250:C497,'Market Returns '!C250:C497)/_xlfn.VAR.S('Market Returns '!C250:C497) -> 0.85889437 | C19: ='Stock Returns'!J11 -> 1.5463539 | E19: ='Market Returns '!H10 -> 0.061212276 | F19: =E19 -> 0.061212276 | H19: =$D$5+B19*(CAPM!E19-CAPM!D5) -> 0.062057177 | I19: Above
A20: Year 3 | B20: =_xlfn.COVARIANCE.S('Stock Returns'!C498:C743,'Market Returns '!C498:C743)/_xlfn.VAR.S('Market Returns '!C498:C743) -> 0.73274519 | C20: ='Stock Returns'!J12 -> 1.7070753 | E20: ='Market Returns '!H11 -> 0.19819022 | F20: =E20 -> 0.19819022 | H20: =$D$5+B20*(CAPM!E20-CAPM!D5) -> 0.16318245 | I20: Above
A21: Year 4 | B21: =_xlfn.COVARIANCE.S('Stock Returns'!C744:C992,'Market Returns '!C744:C992)/_xlfn.VAR.S('Market Returns '!C744:C992) -> 1.0117773 | C21: ='Stock Returns'!J13 -> 1.6301374 | E21: ='Market Returns '!H12 -> 0.093174435 | F21: =E21 -> 0.093174435 | H21: =$D$5+B21*(CAPM!E21-CAPM!D5) -> 0.093480344 | I21: Above
A22: Year 5 | B22: =_xlfn.COVARIANCE.S('Stock Returns'!C993:C1241,'Market Returns '!C993:C1241)/_xlfn.VAR.S('Market Returns '!C993:C1241) -> 1.7914054 | C22: ='Stock Returns'!J14 -> -0.51287528 | E22: ='Market Returns '!H13 -> 0.099174603 | F22: =E22 -> 0.099174603 | H22: =$D$5+B22*(CAPM!E22-CAPM!D5) -> 0.12447948 | I22: Below
